[{
  "_id": {
    "$oid": "654f8bdcec6e4700333e3550"
  },
  "name": "Action",
  "value": 49,
  "_class": "com.tnbm.restapi.models.animes.Top_Genres_Anime"
},
{
  "_id": {
    "$oid": "654f8bdcec6e4700333e3551"
  },
  "name": "Adventure",
  "value": 11,
  "_class": "com.tnbm.restapi.models.animes.Top_Genres_Anime"
},
{
  "_id": {
    "$oid": "654f8bdcec6e4700333e3552"
  },
  "name": "Drama",
  "value": 18,
  "_class": "com.tnbm.restapi.models.animes.Top_Genres_Anime"
},
{
  "_id": {
    "$oid": "654f8bdcec6e4700333e3553"
  },
  "name": "Comedy",
  "value": 7,
  "_class": "com.tnbm.restapi.models.animes.Top_Genres_Anime"
},
{
  "_id": {
    "$oid": "654f8bdcec6e4700333e3554"
  },
  "name": "Supernatural",
  "value": 1,
  "_class": "com.tnbm.restapi.models.animes.Top_Genres_Anime"
},
{
  "_id": {
    "$oid": "654f8bdcec6e4700333e3555"
  },
  "name": "Sports",
  "value": 5,
  "_class": "com.tnbm.restapi.models.animes.Top_Genres_Anime"
},
{
  "_id": {
    "$oid": "654f8bdcec6e4700333e3556"
  },
  "name": "Award Winning",
  "value": 8,
  "_class": "com.tnbm.restapi.models.animes.Top_Genres_Anime"
}]